proxy_www/__init__.py
proxy_www/method.py
proxy_www/old_implementation.py
proxy_www/proxy.py
proxy_www/utils.py
proxy_www-1.1.0.dist-info/METADATA
proxy_www-1.1.0.dist-info/WHEEL
proxy_www-1.1.0.dist-info/top_level.txt
proxy_www-1.1.0.dist-info/RECORD
