Metadata-Version: 2.1
Name: proxy-www
Version: 1.1.0
Summary: Port library of proxy-www in npm (https://github.com/justjavac/proxy-www)
Home-page: https://github.com/Lapis0875/proxy-www.py
Author: Lapis0875
Author-email: lapis0875@kakao.com
License: MIT
Keywords: aiohttp,network,http request,asynchronous,asyncio
Platform: UNKNOWN
Classifier: Programming Language :: Python :: 3
Classifier: License :: OSI Approved :: MIT License
Classifier: Operating System :: OS Independent
Requires-Python: >=3.7
Requires-Dist: 3.7.4.post0
